MANIFEST.in
README.rst
__init__.py
facemtcnn.py
setup.py
face_mtcnn_facenet.egg-info/PKG-INFO
face_mtcnn_facenet.egg-info/SOURCES.txt
face_mtcnn_facenet.egg-info/dependency_links.txt
face_mtcnn_facenet.egg-info/top_level.txt